fuzzy_graph_coloring.py
fuzzy_graph_coloring-0.1.3.dist-info/LICENSE
fuzzy_graph_coloring-0.1.3.dist-info/WHEEL
fuzzy_graph_coloring-0.1.3.dist-info/METADATA
fuzzy_graph_coloring-0.1.3.dist-info/RECORD
