Metadata-Version: 2.1
Name: fuzzy-graph-coloring
Version: 0.1.3
Summary: fuzzy-graph-coloring is a Python package for calculating the fuzzy chromatic number and coloring of a graph with fuzzy edges.
Home-page: https://github.com/ferdinand-dhbw/fuzzy-graph-coloring
License: GPL-3.0-only
Keywords: graph coloring,fuzzy graph,genetic graph coloring,alpha-cut,greedy k-coloring
Author: Ferdinand Koenig and Jonas Rheiner
Requires-Python: >=3.8,<4.0
Classifier: License :: OSI Approved :: GNU General Public License v3 (GPLv3)
Classifier: Programming Language :: Python :: 3
Classifier: Programming Language :: Python :: 3.10
Classifier: Programming Language :: Python :: 3.8
Classifier: Programming Language :: Python :: 3.9
Requires-Dist: matplotlib (>=3.5.1,<4.0.0)
Requires-Dist: networkx (>=2.6.3,<3.0.0)
Requires-Dist: numpy (>=1.22.2,<2.0.0)
Requires-Dist: pygad (>=2.16.3,<3.0.0)
Project-URL: Repository, https://github.com/ferdinand-dhbw/fuzzy-graph-coloring
